{
    "highlight-slices": [
        2,3
    ],
    "highlight-points": [
        [
            "0",
            "5"
        ]
    ],
    "similarity": [
        0.1266541084021253,
        0.08914799295560813,
        0.22633744855967067,
        0.17241379310344843,
        0.23400936037441533,
        0.08979924036896358
    ],
    "timeslices": [
        {
            "nodes": [
                "0",
                "1",
                "2",
                "3",
                "4",
                "5",
                "6",
                "7",
                "8",
                "9",
                "10",
                "11",
                "12",
                "13",
                "14",
                "15",
                "16",
                "17",
                "18",
                "19",
                "20",
                "21",
                "22",
                "23",
                "24",
                "25",
                "26",
                "27",
                "28",
                "29",
                "30",
                "31",
                "32",
                "33",
                "34",
                "35"
            ],
            "links": [
                [
                    "0",
                    "1"
                ],
                [
                    "0",
                    "2"
                ],
                [
                    "0",
                    "7"
                ],
                [
                    "0",
                    "3"
                ],
                [
                    "0",
                    "11"
                ],
                [
                    "0",
                    "12"
                ],
                [
                    "0",
                    "16"
                ],
                [
                    "0",
                    "18"
                ],
                [
                    "0",
                    "21"
                ],
                [
                    "0",
                    "23"
                ],
                [
                    "0",
                    "25"
                ],
                [
                    "0",
                    "28"
                ],
                [
                    "0",
                    "29"
                ],
                [
                    "1",
                    "2"
                ],
                [
                    "1",
                    "3"
                ],
                [
                    "1",
                    "8"
                ],
                [
                    "1",
                    "7"
                ],
                [
                    "1",
                    "5"
                ],
                [
                    "1",
                    "4"
                ],
                [
                    "1",
                    "6"
                ],
                [
                    "1",
                    "12"
                ],
                [
                    "2",
                    "5"
                ],
                [
                    "2",
                    "9"
                ],
                [
                    "2",
                    "13"
                ],
                [
                    "2",
                    "14"
                ],
                [
                    "2",
                    "17"
                ],
                [
                    "2",
                    "20"
                ],
                [
                    "2",
                    "31"
                ],
                [
                    "2",
                    "32"
                ],
                [
                    "2",
                    "33"
                ],
                [
                    "2",
                    "34"
                ],
                [
                    "4",
                    "5"
                ],
                [
                    "4",
                    "7"
                ],
                [
                    "5",
                    "7"
                ],
                [
                    "5",
                    "12"
                ],
                [
                    "5",
                    "15"
                ],
                [
                    "5",
                    "22"
                ],
                [
                    "5",
                    "24"
                ],
                [
                    "5",
                    "26"
                ],
                [
                    "5",
                    "28"
                ],
                [
                    "5",
                    "35"
                ],
                [
                    "7",
                    "10"
                ],
                [
                    "8",
                    "12"
                ],
                [
                    "8",
                    "14"
                ],
                [
                    "8",
                    "19"
                ],
                [
                    "9",
                    "27"
                ],
                [
                    "27",
                    "30"
                ],
                [
                    "30",
                    "32"
                ]
            ],
            "positions": {
                "0": [
                    -0.24105932666977545,
                    -0.207456823815007
                ],
                "1": [
                    -0.06502594661335726,
                    -0.042366244558657895
                ],
                "2": [
                    0.15489487864065138,
                    -0.2836538834956346
                ],
                "3": [
                    -0.24303493806043655,
                    -0.09177475959780827
                ],
                "4": [
                    -0.06476881031822669,
                    0.11146167841657835
                ],
                "5": [
                    0.09803312270042706,
                    0.06636776351190257
                ],
                "6": [
                    -0.20775162880065284,
                    0.15004392295832233
                ],
                "7": [
                    -0.1713185558925544,
                    0.04186727586098366
                ],
                "8": [
                    0.007232804281876594,
                    0.13124364179658793
                ],
                "9": [
                    0.3874892456468964,
                    -0.5013801007017568
                ],
                "10": [
                    -0.3528795930221226,
                    0.2025645548642071
                ],
                "11": [
                    -0.4824920714829021,
                    -0.18560228082684457
                ],
                "12": [
                    -0.0900066305102961,
                    0.0004286650360917387
                ],
                "13": [
                    0.38886308491454424,
                    -0.29176459048705633
                ],
                "14": [
                    0.13489886065260975,
                    -0.07006169940511259
                ],
                "15": [
                    0.25318110181929754,
                    0.2419006811239979
                ],
                "16": [
                    -0.48904974298589166,
                    -0.27789925229670787
                ],
                "17": [
                    0.1616900498171223,
                    -0.49481319304515387
                ],
                "18": [
                    -0.3527611154679442,
                    -0.41446164165973237
                ],
                "19": [
                    -0.038677915892131765,
                    0.37009020289263095
                ],
                "20": [
                    0.07325881951591458,
                    -0.46549799980496365
                ],
                "21": [
                    -0.263789067607809,
                    -0.41173577276956447
                ],
                "22": [
                    0.3073010127774318,
                    0.09656359708574867
                ],
                "23": [
                    -0.44577216216084387,
                    -0.10698349363383514
                ],
                "24": [
                    0.19187959660808857,
                    0.2936773001000735
                ],
                "25": [
                    -0.3966877568146291,
                    -0.2841123946278019
                ],
                "26": [
                    0.3096287102697761,
                    0.18333464038512118
                ],
                "27": [
                    0.5237615217449055,
                    -0.6751158593326116
                ],
                "28": [
                    -0.05747043499643,
                    -0.12001199745645617
                ],
                "29": [
                    -0.43302584013526896,
                    -0.3710740753179301
                ],
                "30": [
                    0.4308977868421816,
                    -0.7416307068376023
                ],
                "31": [
                    0.24664609435571805,
                    -0.4255037989477253
                ],
                "32": [
                    0.2988802420519989,
                    -0.5659052078360419
                ],
                "33": [
                    0.3402149903920214,
                    -0.36840152389441855
                ],
                "34": [
                    0.3381570823161073,
                    -0.21816391954293657
                ],
                "35": [
                    0.10535338345688924,
                    0.2952312576951654
                ]
            }
        },
        {
            "nodes": [
                "0",
                "1",
                "2",
                "4",
                "5",
                "6",
                "7",
                "8",
                "9",
                "10",
                "11",
                "12",
                "13",
                "14",
                "16",
                "17",
                "18",
                "19",
                "21",
                "22",
                "23",
                "24",
                "25",
                "26",
                "27",
                "28",
                "29",
                "30",
                "31",
                "32",
                "33",
                "34",
                "35"
            ],
            "links": [
                [
                    "0",
                    "1"
                ],
                [
                    "0",
                    "2"
                ],
                [
                    "0",
                    "7"
                ],
                [
                    "0",
                    "11"
                ],
                [
                    "0",
                    "16"
                ],
                [
                    "0",
                    "18"
                ],
                [
                    "0",
                    "21"
                ],
                [
                    "0",
                    "23"
                ],
                [
                    "0",
                    "25"
                ],
                [
                    "0",
                    "28"
                ],
                [
                    "0",
                    "29"
                ],
                [
                    "1",
                    "2"
                ],
                [
                    "1",
                    "8"
                ],
                [
                    "1",
                    "7"
                ],
                [
                    "1",
                    "5"
                ],
                [
                    "1",
                    "4"
                ],
                [
                    "1",
                    "6"
                ],
                [
                    "1",
                    "12"
                ],
                [
                    "2",
                    "5"
                ],
                [
                    "2",
                    "9"
                ],
                [
                    "2",
                    "13"
                ],
                [
                    "2",
                    "17"
                ],
                [
                    "2",
                    "31"
                ],
                [
                    "2",
                    "32"
                ],
                [
                    "2",
                    "33"
                ],
                [
                    "2",
                    "34"
                ],
                [
                    "4",
                    "5"
                ],
                [
                    "4",
                    "7"
                ],
                [
                    "5",
                    "7"
                ],
                [
                    "5",
                    "12"
                ],
                [
                    "5",
                    "22"
                ],
                [
                    "5",
                    "24"
                ],
                [
                    "5",
                    "26"
                ],
                [
                    "5",
                    "28"
                ],
                [
                    "5",
                    "35"
                ],
                [
                    "7",
                    "10"
                ],
                [
                    "8",
                    "12"
                ],
                [
                    "8",
                    "14"
                ],
                [
                    "8",
                    "19"
                ],
                [
                    "27",
                    "30"
                ],
                [
                    "30",
                    "32"
                ]
            ],
            "positions": {
                "0": [
                    -0.2235581656727818,
                    -0.2852633457077793
                ],
                "1": [
                    -0.038408343957622916,
                    -0.044485164055577835
                ],
                "2": [
                    0.13548291979086455,
                    -0.3466272976945943
                ],
                "4": [
                    -0.0066949092769708245,
                    0.02402938850698816
                ],
                "5": [
                    0.12241292815660955,
                    -0.030485514407261157
                ],
                "6": [
                    -0.16439798471303732,
                    0.11959625699018238
                ],
                "7": [
                    -0.13022274819053942,
                    -0.06165844226967687
                ],
                "8": [
                    -0.058180876247080446,
                    0.2787148958822433
                ],
                "9": [
                    0.22525367749042424,
                    -0.5037882176175926
                ],
                "10": [
                    -0.31405598702445003,
                    0.05243032647090685
                ],
                "11": [
                    -0.45700545138850146,
                    -0.25673073544492647
                ],
                "12": [
                    0.020613365696622865,
                    0.13121148896839535
                ],
                "13": [
                    0.35593492308532243,
                    -0.37738763944013914
                ],
                "14": [
                    -0.028977920355374494,
                    0.49027434078047716
                ],
                "16": [
                    -0.46053598192122963,
                    -0.3605206229614998
                ],
                "17": [
                    0.06506140336477668,
                    -0.5150486547235622
                ],
                "18": [
                    -0.3207794311728028,
                    -0.48733379290790846
                ],
                "19": [
                    -0.14636629823252686,
                    0.47204888227674274
                ],
                "21": [
                    -0.2306212715065638,
                    -0.47529692503932647
                ],
                "22": [
                    0.32410501865655783,
                    -0.032168704121570295
                ],
                "23": [
                    -0.39876437555072,
                    -0.1848342529830746
                ],
                "24": [
                    0.28181073120825684,
                    0.13341837138993168
                ],
                "25": [
                    -0.3717397086323186,
                    -0.33881979810834434
                ],
                "26": [
                    0.3273403375049297,
                    0.05864365153596282
                ],
                "27": [
                    0.6035898517299106,
                    -0.9891214511712233
                ],
                "28": [
                    -0.04534687288265567,
                    -0.1818947252804226
                ],
                "29": [
                    -0.3986852852868236,
                    -0.4442191806855517
                ],
                "30": [
                    0.4931101132341381,
                    -0.8359229712225023
                ],
                "31": [
                    0.14885204339577643,
                    -0.5626549541618839
                ],
                "32": [
                    0.3380131837401427,
                    -0.6236054380988608
                ],
                "33": [
                    0.30798859680295687,
                    -0.45569968250952403
                ],
                "34": [
                    0.30894249306749677,
                    -0.29892523152864753
                ],
                "35": [
                    0.19858600040299404,
                    0.16830944706253567
                ]
            }
        },
        {
            "nodes": [
                "0",
                "1",
                "2",
                "3",
                "4",
                "5",
                "7",
                "9",
                "11",
                "12",
                "14",
                "16",
                "17",
                "22",
                "25",
                "26",
                "27",
                "28",
                "30",
                "31",
                "32",
                "34"
            ],
            "links": [
                [
                    "0",
                    "2"
                ],
                [
                    "0",
                    "7"
                ],
                [
                    "0",
                    "3"
                ],
                [
                    "0",
                    "11"
                ],
                [
                    "0",
                    "16"
                ],
                [
                    "0",
                    "25"
                ],
                [
                    "1",
                    "2"
                ],
                [
                    "1",
                    "5"
                ],
                [
                    "1",
                    "4"
                ],
                [
                    "1",
                    "12"
                ],
                [
                    "2",
                    "5"
                ],
                [
                    "2",
                    "14"
                ],
                [
                    "2",
                    "17"
                ],
                [
                    "2",
                    "31"
                ],
                [
                    "2",
                    "32"
                ],
                [
                    "2",
                    "34"
                ],
                [
                    "4",
                    "5"
                ],
                [
                    "4",
                    "7"
                ],
                [
                    "5",
                    "7"
                ],
                [
                    "5",
                    "22"
                ],
                [
                    "5",
                    "26"
                ],
                [
                    "5",
                    "28"
                ],
                [
                    "9",
                    "27"
                ],
                [
                    "30",
                    "32"
                ]
            ],
            "positions": {
                "0": [
                    -0.2561558526072102,
                    -0.2961641795253558
                ],
                "1": [
                    -0.0004256048834795044,
                    -0.0871799776959164
                ],
                "2": [
                    0.046120986108845914,
                    -0.3084159611480682
                ],
                "3": [
                    -0.33462720256175693,
                    -0.45885638793599115
                ],
                "4": [
                    -0.03784768401866159,
                    -0.00878760250804403
                ],
                "5": [
                    0.09241935190397386,
                    -0.03921400847498809
                ],
                "7": [
                    -0.1092580281680599,
                    -0.12597164083722784
                ],
                "9": [
                    2.459600780620731,
                    -2.5643145154152167
                ],
                "11": [
                    -0.40755753508511944,
                    -0.19719998218187126
                ],
                "12": [
                    -0.09377776128179806,
                    0.0934915040840127
                ],
                "14": [
                    0.19259867336264763,
                    -0.39002060021534507
                ],
                "16": [
                    -0.4219163660027905,
                    -0.39647823729218673
                ],
                "17": [
                    -0.03817569418074665,
                    -0.4531945434023111
                ],
                "22": [
                    0.27518569927122233,
                    0.014687029213908914
                ],
                "25": [
                    -0.44849861390511514,
                    -0.296381293102672
                ],
                "26": [
                    0.21929548518964148,
                    0.1143929044199902
                ],
                "27": [
                    2.5395163092732904,
                    -2.639409787028452
                ],
                "28": [
                    0.1136267641718531,
                    0.15652777321619443
                ],
                "30": [
                    0.31283366186712164,
                    -0.6728863477148341
                ],
                "31": [
                    0.0656395027683927,
                    -0.4810991017516362
                ],
                "32": [
                    0.20189132107861057,
                    -0.5226994164103925
                ],
                "34": [
                    0.21924027087627787,
                    -0.28744743330998473
                ]
            }
        },
        {
            "nodes": [
                "0",
                "1",
                "2",
                "4",
                "5",
                "7",
                "8",
                "9",
                "11",
                "12",
                "14",
                "16",
                "19",
                "20",
                "22",
                "24",
                "25",
                "26",
                "27",
                "30",
                "32",
                "33",
                "34",
                "35"
            ],
            "links": [
                [
                    "0",
                    "1"
                ],
                [
                    "0",
                    "7"
                ],
                [
                    "0",
                    "11"
                ],
                [
                    "0",
                    "12"
                ],
                [
                    "0",
                    "16"
                ],
                [
                    "0",
                    "25"
                ],
                [
                    "1",
                    "5"
                ],
                [
                    "1",
                    "12"
                ],
                [
                    "2",
                    "9"
                ],
                [
                    "2",
                    "14"
                ],
                [
                    "2",
                    "20"
                ],
                [
                    "2",
                    "33"
                ],
                [
                    "2",
                    "34"
                ],
                [
                    "4",
                    "7"
                ],
                [
                    "5",
                    "22"
                ],
                [
                    "5",
                    "24"
                ],
                [
                    "5",
                    "26"
                ],
                [
                    "5",
                    "35"
                ],
                [
                    "8",
                    "12"
                ],
                [
                    "8",
                    "14"
                ],
                [
                    "8",
                    "19"
                ],
                [
                    "9",
                    "27"
                ],
                [
                    "27",
                    "30"
                ],
                [
                    "30",
                    "32"
                ]
            ],
            "positions": {
                "0": [
                    -0.2708849555523447,
                    -0.2281152146727651
                ],
                "1": [
                    -0.10596016227752658,
                    -0.08241497710743825
                ],
                "2": [
                    0.6313624633791479,
                    -1.0360818492264885
                ],
                "4": [
                    -0.6830496232392903,
                    -0.18021198262892335
                ],
                "5": [
                    -0.06588350044488668,
                    0.20713397222505003
                ],
                "7": [
                    -0.5100902034844454,
                    -0.19752121391466665
                ],
                "8": [
                    0.18573274538154527,
                    -0.5727540209668204
                ],
                "9": [
                    0.827587672886807,
                    -1.23780816463155
                ],
                "11": [
                    -0.36213536338819546,
                    -0.11202674456131223
                ],
                "12": [
                    -0.03394509680376179,
                    -0.32217349918370763
                ],
                "14": [
                    0.4124027965570321,
                    -0.8055557366382765
                ],
                "16": [
                    -0.41033166108499486,
                    -0.3033053740924809
                ],
                "19": [
                    0.14778395959749874,
                    -0.6873312983298314
                ],
                "20": [
                    0.606594207547449,
                    -1.1667443458269275
                ],
                "22": [
                    -0.08694916636740668,
                    0.3887798119146791
                ],
                "24": [
                    0.04994889576664937,
                    0.31769274099116124
                ],
                "25": [
                    -0.3095870339059488,
                    -0.3732068765394609
                ],
                "26": [
                    -0.18592118396452834,
                    0.31728216987002916
                ],
                "27": [
                    0.9903765219649987,
                    -1.417613254687733
                ],
                "30": [
                    1.1274651578266233,
                    -1.5732232602843286
                ],
                "32": [
                    1.232200237463819,
                    -1.6937226763546602
                ],
                "33": [
                    0.606594207547449,
                    -1.1667443458269275
                ],
                "34": [
                    0.7681381572973685,
                    -0.9817166099914578
                ],
                "35": [
                    0.04994889576664937,
                    0.31769274099116124
                ]
            }
        },
        {
            "nodes": [
                "0",
                "1",
                "2",
                "3",
                "4",
                "5",
                "7",
                "8",
                "9",
                "11",
                "12",
                "13",
                "14",
                "16",
                "17",
                "18",
                "19",
                "20",
                "21",
                "23",
                "24",
                "25",
                "26",
                "27",
                "28",
                "29",
                "30",
                "31",
                "32",
                "33",
                "34",
                "35"
            ],
            "links": [
                [
                    "0",
                    "1"
                ],
                [
                    "0",
                    "2"
                ],
                [
                    "0",
                    "3"
                ],
                [
                    "0",
                    "11"
                ],
                [
                    "0",
                    "16"
                ],
                [
                    "0",
                    "18"
                ],
                [
                    "0",
                    "21"
                ],
                [
                    "0",
                    "23"
                ],
                [
                    "0",
                    "25"
                ],
                [
                    "0",
                    "28"
                ],
                [
                    "0",
                    "29"
                ],
                [
                    "1",
                    "2"
                ],
                [
                    "1",
                    "3"
                ],
                [
                    "1",
                    "8"
                ],
                [
                    "1",
                    "7"
                ],
                [
                    "1",
                    "4"
                ],
                [
                    "1",
                    "12"
                ],
                [
                    "2",
                    "13"
                ],
                [
                    "2",
                    "14"
                ],
                [
                    "2",
                    "17"
                ],
                [
                    "2",
                    "20"
                ],
                [
                    "2",
                    "31"
                ],
                [
                    "2",
                    "33"
                ],
                [
                    "2",
                    "34"
                ],
                [
                    "4",
                    "5"
                ],
                [
                    "4",
                    "7"
                ],
                [
                    "5",
                    "7"
                ],
                [
                    "5",
                    "12"
                ],
                [
                    "5",
                    "24"
                ],
                [
                    "5",
                    "26"
                ],
                [
                    "5",
                    "28"
                ],
                [
                    "5",
                    "35"
                ],
                [
                    "8",
                    "12"
                ],
                [
                    "8",
                    "14"
                ],
                [
                    "8",
                    "19"
                ],
                [
                    "9",
                    "27"
                ],
                [
                    "27",
                    "30"
                ],
                [
                    "30",
                    "32"
                ]
            ],
            "positions": {
                "0": [
                    -0.00383034126302945,
                    -0.39042208343458956
                ],
                "1": [
                    0.2448428284489978,
                    -0.25051631461113477
                ],
                "2": [
                    0.3190291465223629,
                    -0.55031987557504
                ],
                "3": [
                    0.12076028651451079,
                    -0.32277679600382536
                ],
                "4": [
                    0.2534958127142742,
                    -0.026221380171110642
                ],
                "5": [
                    0.18744981312803807,
                    0.11280574787505866
                ],
                "7": [
                    0.1900364565786174,
                    -0.042910784497335534
                ],
                "8": [
                    0.4587815703493041,
                    -0.19888456798745727
                ],
                "9": [
                    2.4807765164289353,
                    -3.594569190461192
                ],
                "11": [
                    -0.20436906633747565,
                    -0.30965936199006777
                ],
                "12": [
                    0.33532773268920213,
                    -0.06897515785853743
                ],
                "13": [
                    0.4509808161807032,
                    -0.7052543692402536
                ],
                "14": [
                    0.45516892549538673,
                    -0.3866741949691324
                ],
                "16": [
                    -0.22893908590525217,
                    -0.39976320554351585
                ],
                "17": [
                    0.4509808161807032,
                    -0.7052543692402536
                ],
                "18": [
                    -0.12994466299278543,
                    -0.5336874873365224
                ],
                "19": [
                    0.6470850808215272,
                    -0.12871638146090958
                ],
                "20": [
                    0.2769290377672119,
                    -0.743858100154341
                ],
                "21": [
                    -0.12994466299278543,
                    -0.5336874873365224
                ],
                "23": [
                    -0.12994466299278543,
                    -0.5336874873365224
                ],
                "24": [
                    0.22772939776668086,
                    0.31042293654547215
                ],
                "25": [
                    -0.13054916131005978,
                    -0.2522249766058422
                ],
                "26": [
                    0.08043587772412882,
                    0.2882041638467572
                ],
                "27": [
                    2.352569453080306,
                    -3.584547069869154
                ],
                "28": [
                    0.048286707874330786,
                    -0.10899819414391813
                ],
                "29": [
                    -0.12994466299278543,
                    -0.5336874873365224
                ],
                "30": [
                    2.2367280276837023,
                    -3.6546749461339734
                ],
                "31": [
                    0.4509808161807032,
                    -0.7052543692402536
                ],
                "32": [
                    2.1884104708882335,
                    -3.773427736724026
                ],
                "33": [
                    0.2769290377672119,
                    -0.743858100154341
                ],
                "34": [
                    0.5203088099290639,
                    -0.5690435427987143
                ],
                "35": [
                    0.22772939776668086,
                    0.31042293654547215
                ]
            }
        },
        {
            "nodes": [
                "0",
                "1",
                "2",
                "3",
                "4",
                "5",
                "7",
                "8",
                "9",
                "10",
                "11",
                "12",
                "13",
                "14",
                "16",
                "17",
                "18",
                "19",
                "20",
                "21",
                "22",
                "23",
                "24",
                "25",
                "26",
                "27",
                "28",
                "29",
                "30",
                "31",
                "32",
                "33",
                "34",
                "35"
            ],
            "links": [
                [
                    "0",
                    "1"
                ],
                [
                    "0",
                    "2"
                ],
                [
                    "0",
                    "7"
                ],
                [
                    "0",
                    "3"
                ],
                [
                    "0",
                    "11"
                ],
                [
                    "0",
                    "12"
                ],
                [
                    "0",
                    "16"
                ],
                [
                    "0",
                    "18"
                ],
                [
                    "0",
                    "21"
                ],
                [
                    "0",
                    "23"
                ],
                [
                    "0",
                    "25"
                ],
                [
                    "0",
                    "28"
                ],
                [
                    "0",
                    "29"
                ],
                [
                    "1",
                    "2"
                ],
                [
                    "1",
                    "3"
                ],
                [
                    "1",
                    "7"
                ],
                [
                    "1",
                    "5"
                ],
                [
                    "1",
                    "4"
                ],
                [
                    "1",
                    "12"
                ],
                [
                    "2",
                    "5"
                ],
                [
                    "2",
                    "9"
                ],
                [
                    "2",
                    "13"
                ],
                [
                    "2",
                    "14"
                ],
                [
                    "2",
                    "17"
                ],
                [
                    "2",
                    "20"
                ],
                [
                    "2",
                    "31"
                ],
                [
                    "2",
                    "32"
                ],
                [
                    "2",
                    "33"
                ],
                [
                    "2",
                    "34"
                ],
                [
                    "4",
                    "5"
                ],
                [
                    "4",
                    "7"
                ],
                [
                    "5",
                    "7"
                ],
                [
                    "5",
                    "12"
                ],
                [
                    "5",
                    "22"
                ],
                [
                    "5",
                    "24"
                ],
                [
                    "5",
                    "26"
                ],
                [
                    "5",
                    "28"
                ],
                [
                    "5",
                    "35"
                ],
                [
                    "7",
                    "10"
                ],
                [
                    "8",
                    "12"
                ],
                [
                    "8",
                    "14"
                ],
                [
                    "8",
                    "19"
                ],
                [
                    "9",
                    "27"
                ],
                [
                    "30",
                    "32"
                ]
            ],
            "positions": {
                "0": [
                    0.19688418809118668,
                    -0.6768349101492858
                ],
                "1": [
                    0.3358749754528141,
                    -0.5387298528195481
                ],
                "2": [
                    0.5947384194706509,
                    -0.6920524223346698
                ],
                "3": [
                    0.17437576252010495,
                    -0.5865334979951891
                ],
                "4": [
                    0.26435447844565596,
                    -0.3720210046353176
                ],
                "5": [
                    0.3819332456841743,
                    -0.36291947114069356
                ],
                "7": [
                    0.17832222564132488,
                    -0.4339335171087317
                ],
                "8": [
                    0.6601692214054771,
                    -0.34954494959187027
                ],
                "9": [
                    0.9031458342878629,
                    -0.7943574076834461
                ],
                "10": [
                    -0.008519795405599854,
                    -0.2967242452962933
                ],
                "11": [
                    -0.05253851999030685,
                    -0.6870247348685637
                ],
                "12": [
                    0.4239103160795304,
                    -0.48961606773730026
                ],
                "13": [
                    0.7870804118894918,
                    -0.6734901762890438
                ],
                "14": [
                    0.6939652171924949,
                    -0.4994796275561937
                ],
                "16": [
                    -0.021967711218279645,
                    -0.7652961775832234
                ],
                "17": [
                    0.7870804118894918,
                    -0.6734901762890438
                ],
                "18": [
                    0.09924980286857882,
                    -0.8629064046662311
                ],
                "19": [
                    0.8132880818262419,
                    -0.19848450552877592
                ],
                "20": [
                    0.5862058820203124,
                    -0.8834515647759843
                ],
                "21": [
                    0.09924980286857882,
                    -0.8629064046662311
                ],
                "22": [
                    0.49639106389638255,
                    -0.1817695431713452
                ],
                "23": [
                    0.09924980286857882,
                    -0.8629064046662311
                ],
                "24": [
                    0.3797791177562567,
                    -0.1368048576486238
                ],
                "25": [
                    -0.01612288712722055,
                    -0.6027154561730603
                ],
                "26": [
                    0.25798906379672115,
                    -0.1712716892216706
                ],
                "27": [
                    1.1131500633450004,
                    -0.8575403221539081
                ],
                "28": [
                    0.24400937814231338,
                    -0.49972063053155236
                ],
                "29": [
                    0.09924980286857882,
                    -0.8629064046662311
                ],
                "30": [
                    0.8576603070422513,
                    -1.1531083834672324
                ],
                "31": [
                    0.7870804118894918,
                    -0.6734901762890438
                ],
                "32": [
                    0.7506278171108626,
                    -0.9675425971249981
                ],
                "33": [
                    0.5862058820203124,
                    -0.8834515647759843
                ],
                "34": [
                    0.7253599077548849,
                    -0.8342976735562657
                ],
                "35": [
                    0.3797791177562567,
                    -0.1368048576486238
                ]
            }
        }
    ]
}