{
    "highlight-slices": [
        2,3
    ],
    "highlight-points": [
        [
            "0",
            "5"
        ]
    ],
    "similarity": [
        0.1266541084021253,
        0.08914799295560813,
        0.22633744855967067,
        0.17241379310344843,
        0.23400936037441533,
        0.08979924036896358
    ],
    "timeslices": [
        {
            "nodes": [
                "0",
                "1",
                "2",
                "3",
                "4",
                "5",
                "6",
                "7",
                "8",
                "9",
                "10",
                "11",
                "12",
                "13",
                "14",
                "15",
                "16",
                "17",
                "18",
                "19",
                "20",
                "21",
                "22",
                "23",
                "24",
                "25",
                "26",
                "27",
                "28",
                "29",
                "30",
                "31",
                "32",
                "33",
                "34",
                "35"
            ],
            "links": [
                [
                    "0",
                    "1"
                ],
                [
                    "0",
                    "2"
                ],
                [
                    "0",
                    "7"
                ],
                [
                    "0",
                    "3"
                ],
                [
                    "0",
                    "11"
                ],
                [
                    "0",
                    "12"
                ],
                [
                    "0",
                    "16"
                ],
                [
                    "0",
                    "18"
                ],
                [
                    "0",
                    "21"
                ],
                [
                    "0",
                    "23"
                ],
                [
                    "0",
                    "25"
                ],
                [
                    "0",
                    "28"
                ],
                [
                    "0",
                    "29"
                ],
                [
                    "1",
                    "2"
                ],
                [
                    "1",
                    "3"
                ],
                [
                    "1",
                    "8"
                ],
                [
                    "1",
                    "7"
                ],
                [
                    "1",
                    "5"
                ],
                [
                    "1",
                    "4"
                ],
                [
                    "1",
                    "6"
                ],
                [
                    "1",
                    "12"
                ],
                [
                    "2",
                    "5"
                ],
                [
                    "2",
                    "9"
                ],
                [
                    "2",
                    "13"
                ],
                [
                    "2",
                    "14"
                ],
                [
                    "2",
                    "17"
                ],
                [
                    "2",
                    "20"
                ],
                [
                    "2",
                    "31"
                ],
                [
                    "2",
                    "32"
                ],
                [
                    "2",
                    "33"
                ],
                [
                    "2",
                    "34"
                ],
                [
                    "4",
                    "5"
                ],
                [
                    "4",
                    "7"
                ],
                [
                    "5",
                    "7"
                ],
                [
                    "5",
                    "12"
                ],
                [
                    "5",
                    "15"
                ],
                [
                    "5",
                    "22"
                ],
                [
                    "5",
                    "24"
                ],
                [
                    "5",
                    "26"
                ],
                [
                    "5",
                    "28"
                ],
                [
                    "5",
                    "35"
                ],
                [
                    "7",
                    "10"
                ],
                [
                    "8",
                    "12"
                ],
                [
                    "8",
                    "14"
                ],
                [
                    "8",
                    "19"
                ],
                [
                    "9",
                    "27"
                ],
                [
                    "27",
                    "30"
                ],
                [
                    "30",
                    "32"
                ]
            ],
            "positions": {
                "0": [
                    -0.06965139839791226,
                    -0.0184725721063859
                ],
                "1": [
                    0.005928214940910614,
                    0.0004950797701466585
                ],
                "2": [
                    0.022731972171284906,
                    0.10495501992567925
                ],
                "3": [
                    -0.209684727552936,
                    0.024399737463102596
                ],
                "4": [
                    -0.10267234750859824,
                    0.05401289640301163
                ],
                "5": [
                    -0.002722301406940272,
                    -0.07816142876576426
                ],
                "6": [
                    0.4368947646386064,
                    -0.14127377696060595
                ],
                "7": [
                    -0.07516352776786452,
                    -0.10233740288665566
                ],
                "8": [
                    0.16715450676382637,
                    -0.022609533423662145
                ],
                "9": [
                    0.3245935089942678,
                    0.23169804657708457
                ],
                "10": [
                    0.21766557503574807,
                    -0.5289606693941227
                ],
                "11": [
                    -0.3847100867755154,
                    -0.34903202792849763
                ],
                "12": [
                    0.07170608356771702,
                    -0.06515194836748708
                ],
                "13": [
                    -0.3349106511253501,
                    0.38814400435684393
                ],
                "14": [
                    0.1783512863711639,
                    0.13831293740534192
                ],
                "15": [
                    -0.14875874023952484,
                    -0.5108761699984714
                ],
                "16": [
                    -0.4281249652053825,
                    0.23994308189428093
                ],
                "17": [
                    0.13482576827997242,
                    0.5156887782459902
                ],
                "18": [
                    -0.5138324652776559,
                    -0.007951076398365634
                ],
                "19": [
                    0.6183018630054776,
                    -0.1277371382491832
                ],
                "20": [
                    -0.128281098336034,
                    0.5040926627249546
                ],
                "21": [
                    -0.49966791371222,
                    -0.13973821483936033
                ],
                "22": [
                    -0.2786623738685415,
                    -0.4434571949289897
                ],
                "23": [
                    -0.49116992780447216,
                    0.12380142902331487
                ],
                "24": [
                    0.10642319789054218,
                    -0.49533044221698147
                ],
                "25": [
                    0.34082864273422825,
                    -0.29147071316753836
                ],
                "26": [
                    0.32018674006251036,
                    -0.3923327696913591
                ],
                "27": [
                    0.5096597015656207,
                    0.3668718113926828
                ],
                "28": [
                    -0.056409467440545355,
                    -0.21991962084892264
                ],
                "29": [
                    -0.057453498703509125,
                    -0.49081093292717065
                ],
                "30": [
                    0.35246213106463353,
                    0.5269207704683809
                ],
                "31": [
                    -0.2374185351112131,
                    0.4578955438628536
                ],
                "32": [
                    0.16587943014844805,
                    0.3564478079448862
                ],
                "33": [
                    0.49643885675147925,
                    0.12027197164217865
                ],
                "34": [
                    -0.007997687243667628,
                    0.5261968217770499
                ],
                "35": [
                    -0.44274053050855566,
                    -0.25452476777826033
                ]
            }
        },
        {
            "nodes": [
                "0",
                "1",
                "2",
                "4",
                "5",
                "6",
                "7",
                "8",
                "9",
                "10",
                "11",
                "12",
                "13",
                "14",
                "16",
                "17",
                "18",
                "19",
                "21",
                "22",
                "23",
                "24",
                "25",
                "26",
                "27",
                "28",
                "29",
                "30",
                "31",
                "32",
                "33",
                "34",
                "35"
            ],
            "links": [
                [
                    "0",
                    "1"
                ],
                [
                    "0",
                    "2"
                ],
                [
                    "0",
                    "7"
                ],
                [
                    "0",
                    "11"
                ],
                [
                    "0",
                    "16"
                ],
                [
                    "0",
                    "18"
                ],
                [
                    "0",
                    "21"
                ],
                [
                    "0",
                    "23"
                ],
                [
                    "0",
                    "25"
                ],
                [
                    "0",
                    "28"
                ],
                [
                    "0",
                    "29"
                ],
                [
                    "1",
                    "2"
                ],
                [
                    "1",
                    "8"
                ],
                [
                    "1",
                    "7"
                ],
                [
                    "1",
                    "5"
                ],
                [
                    "1",
                    "4"
                ],
                [
                    "1",
                    "6"
                ],
                [
                    "1",
                    "12"
                ],
                [
                    "2",
                    "5"
                ],
                [
                    "2",
                    "9"
                ],
                [
                    "2",
                    "13"
                ],
                [
                    "2",
                    "17"
                ],
                [
                    "2",
                    "31"
                ],
                [
                    "2",
                    "32"
                ],
                [
                    "2",
                    "33"
                ],
                [
                    "2",
                    "34"
                ],
                [
                    "4",
                    "5"
                ],
                [
                    "4",
                    "7"
                ],
                [
                    "5",
                    "7"
                ],
                [
                    "5",
                    "12"
                ],
                [
                    "5",
                    "22"
                ],
                [
                    "5",
                    "24"
                ],
                [
                    "5",
                    "26"
                ],
                [
                    "5",
                    "28"
                ],
                [
                    "5",
                    "35"
                ],
                [
                    "7",
                    "10"
                ],
                [
                    "8",
                    "12"
                ],
                [
                    "8",
                    "14"
                ],
                [
                    "8",
                    "19"
                ],
                [
                    "27",
                    "30"
                ],
                [
                    "30",
                    "32"
                ]
            ],
            "positions": {
                "0": [
                    -0.08167617798961756,
                    -0.034161673297151154
                ],
                "1": [
                    0.005718626932675294,
                    -0.016079873587866066
                ],
                "2": [
                    -0.005541064082741156,
                    0.05589975822341338
                ],
                "4": [
                    -0.05596604219402327,
                    0.011246099899273065
                ],
                "5": [
                    -0.0038132517711789863,
                    -0.05522670829875823
                ],
                "6": [
                    0.25796145766477385,
                    -0.10950498401693999
                ],
                "7": [
                    -0.036000862373068765,
                    -0.07774380531870116
                ],
                "8": [
                    0.13660882267633512,
                    -0.016785978428458307
                ],
                "9": [
                    0.19012904073271575,
                    0.18036524888162928
                ],
                "10": [
                    0.10748140119378657,
                    -0.34681603627444674
                ],
                "11": [
                    -0.2605327968349548,
                    -0.24152759488855038
                ],
                "12": [
                    0.0668500644995367,
                    -0.06314814618782082
                ],
                "13": [
                    -0.20949149811133602,
                    0.2318379161476044
                ],
                "14": [
                    0.330741262415933,
                    0.10889092993529803
                ],
                "16": [
                    -0.27037512322203305,
                    0.13206513198942402
                ],
                "17": [
                    0.04008592388827798,
                    0.293929558087291
                ],
                "18": [
                    -0.32992877732150144,
                    -0.020190214055324857
                ],
                "19": [
                    0.4128366206237052,
                    -0.11862398058663286
                ],
                "21": [
                    -0.3272848048609185,
                    -0.1074652059579821
                ],
                "22": [
                    -0.1563407182364678,
                    -0.2899542605784359
                ],
                "23": [
                    -0.31342204353532704,
                    0.06182133516179226
                ],
                "24": [
                    0.031078179574512393,
                    -0.31965229520067323
                ],
                "25": [
                    0.13948145309341972,
                    -0.23825772866601075
                ],
                "26": [
                    0.20071405878447843,
                    -0.24048888084416306
                ],
                "27": [
                    0.5287201923308615,
                    0.46290965352196567
                ],
                "28": [
                    -0.07585895914629541,
                    -0.1336000832306427
                ],
                "29": [
                    -0.08870316651736793,
                    -0.3271163325504758
                ],
                "30": [
                    0.2998230117182262,
                    0.45279258045545423
                ],
                "31": [
                    -0.14203197182048485,
                    0.27353121677364733
                ],
                "32": [
                    0.13240213101533374,
                    0.26597214796489915
                ],
                "33": [
                    0.26587983667647197,
                    0.08215040479577099
                ],
                "34": [
                    -0.044542567169648654,
                    0.30143893841974817
                ],
                "35": [
                    -0.25718409683616533,
                    -0.166274734092888
                ]
            }
        },
        {
            "nodes": [
                "0",
                "1",
                "2",
                "3",
                "4",
                "5",
                "7",
                "9",
                "11",
                "12",
                "14",
                "16",
                "17",
                "22",
                "25",
                "26",
                "27",
                "28",
                "30",
                "31",
                "32",
                "34"
            ],
            "links": [
                [
                    "0",
                    "2"
                ],
                [
                    "0",
                    "7"
                ],
                [
                    "0",
                    "3"
                ],
                [
                    "0",
                    "11"
                ],
                [
                    "0",
                    "16"
                ],
                [
                    "0",
                    "25"
                ],
                [
                    "1",
                    "2"
                ],
                [
                    "1",
                    "5"
                ],
                [
                    "1",
                    "4"
                ],
                [
                    "1",
                    "12"
                ],
                [
                    "2",
                    "5"
                ],
                [
                    "2",
                    "14"
                ],
                [
                    "2",
                    "17"
                ],
                [
                    "2",
                    "31"
                ],
                [
                    "2",
                    "32"
                ],
                [
                    "2",
                    "34"
                ],
                [
                    "4",
                    "5"
                ],
                [
                    "4",
                    "7"
                ],
                [
                    "5",
                    "7"
                ],
                [
                    "5",
                    "22"
                ],
                [
                    "5",
                    "26"
                ],
                [
                    "5",
                    "28"
                ],
                [
                    "9",
                    "27"
                ],
                [
                    "30",
                    "32"
                ]
            ],
            "positions": {
                "0": [
                    -0.2150855686746525,
                    -0.03427822028007657
                ],
                "1": [
                    0.0578158441761767,
                    -0.0007073148639051008
                ],
                "2": [
                    -0.031087542712908194,
                    0.09211522585539961
                ],
                "3": [
                    -0.5333127060905846,
                    -0.05951729864406412
                ],
                "4": [
                    -0.07757660809565652,
                    0.0027068584792253603
                ],
                "5": [
                    -0.004185426001130324,
                    -0.07512207413715179
                ],
                "7": [
                    -0.1059866219379764,
                    -0.10361073277175162
                ],
                "9": [
                    0.5266863439763805,
                    0.29269180712371307
                ],
                "11": [
                    -0.3919907216430942,
                    -0.2806177925271921
                ],
                "12": [
                    0.2935174078798054,
                    -0.13246854102709787
                ],
                "14": [
                    0.3179401535111548,
                    0.10031692968052411
                ],
                "16": [
                    -0.4328260984280174,
                    0.15592697081439433
                ],
                "17": [
                    0.011181667265257038,
                    0.36664363472276307
                ],
                "22": [
                    -0.19409697625227074,
                    -0.36081744118362985
                ],
                "25": [
                    0.06065534075941259,
                    -0.3696396441574286
                ],
                "26": [
                    0.24224527823496883,
                    -0.2926508976173746
                ],
                "27": [
                    0.6576459733305164,
                    0.5147586441232199
                ],
                "28": [
                    -0.047657099050558885,
                    -0.33739626785868465
                ],
                "30": [
                    0.2959100360938377,
                    0.5821526916037059
                ],
                "31": [
                    -0.2522068339172603,
                    0.3096904869789806
                ],
                "32": [
                    0.16741562688317832,
                    0.3194597658508008
                ],
                "34": [
                    -0.12652415886320978,
                    0.37190126844350585
                ]
            }
        },
        {
            "nodes": [
                "0",
                "1",
                "2",
                "4",
                "5",
                "7",
                "8",
                "9",
                "11",
                "12",
                "14",
                "16",
                "19",
                "20",
                "22",
                "24",
                "25",
                "26",
                "27",
                "30",
                "32",
                "33",
                "34",
                "35"
            ],
            "links": [
                [
                    "0",
                    "1"
                ],
                [
                    "0",
                    "7"
                ],
                [
                    "0",
                    "11"
                ],
                [
                    "0",
                    "12"
                ],
                [
                    "0",
                    "16"
                ],
                [
                    "0",
                    "25"
                ],
                [
                    "1",
                    "5"
                ],
                [
                    "1",
                    "12"
                ],
                [
                    "2",
                    "9"
                ],
                [
                    "2",
                    "14"
                ],
                [
                    "2",
                    "20"
                ],
                [
                    "2",
                    "33"
                ],
                [
                    "2",
                    "34"
                ],
                [
                    "4",
                    "7"
                ],
                [
                    "5",
                    "22"
                ],
                [
                    "5",
                    "24"
                ],
                [
                    "5",
                    "26"
                ],
                [
                    "5",
                    "35"
                ],
                [
                    "8",
                    "12"
                ],
                [
                    "8",
                    "14"
                ],
                [
                    "8",
                    "19"
                ],
                [
                    "9",
                    "27"
                ],
                [
                    "27",
                    "30"
                ],
                [
                    "30",
                    "32"
                ]
            ],
            "positions": {
                "0": [
                    -0.07152965087911867,
                    -0.10042138324888583
                ],
                "1": [
                    -0.0001947896532557003,
                    -0.13332087119323247
                ],
                "2": [
                    0.18993118982733626,
                    0.2271327189392055
                ],
                "4": [
                    -0.29259806664741955,
                    -0.048077543707836456
                ],
                "5": [
                    0.05507053705013942,
                    -0.24801612618698973
                ],
                "7": [
                    -0.1844757999296937,
                    -0.08474265063144745
                ],
                "8": [
                    0.05669160094763298,
                    0.040856815068628316
                ],
                "9": [
                    0.3151978982489021,
                    0.2928454884943386
                ],
                "11": [
                    -0.18238273599605914,
                    -0.175935184894408
                ],
                "12": [
                    0.006210185439536442,
                    -0.06908065396991275
                ],
                "14": [
                    0.15663905713788973,
                    0.1137526935447544
                ],
                "16": [
                    -0.15982869315216447,
                    -0.007191625809496616
                ],
                "19": [
                    -0.028259255518327253,
                    0.12642527254558097
                ],
                "20": [
                    0.3009723786708872,
                    0.17743878626944795
                ],
                "22": [
                    -0.038244336046675265,
                    -0.3480761178623522
                ],
                "24": [
                    0.05727365511667537,
                    -0.36776669583501514
                ],
                "25": [
                    -0.09126455896064312,
                    -0.2136083476529032
                ],
                "26": [
                    0.1808565427402582,
                    -0.25731180446646085
                ],
                "27": [
                    0.3938741750859892,
                    0.3891709261939377
                ],
                "30": [
                    0.3675378270795633,
                    0.5046074645117468
                ],
                "32": [
                    0.2955317630721159,
                    0.5795250958266064
                ],
                "33": [
                    0.17351075488983858,
                    0.32887607124830437
                ],
                "34": [
                    0.08075454570256574,
                    0.313848876636486
                ],
                "35": [
                    0.13963577479682426,
                    -0.3303858375491915
                ]
            }
        },
        {
            "nodes": [
                "0",
                "1",
                "2",
                "3",
                "4",
                "5",
                "7",
                "8",
                "9",
                "11",
                "12",
                "13",
                "14",
                "16",
                "17",
                "18",
                "19",
                "20",
                "21",
                "23",
                "24",
                "25",
                "26",
                "27",
                "28",
                "29",
                "30",
                "31",
                "32",
                "33",
                "34",
                "35"
            ],
            "links": [
                [
                    "0",
                    "1"
                ],
                [
                    "0",
                    "2"
                ],
                [
                    "0",
                    "3"
                ],
                [
                    "0",
                    "11"
                ],
                [
                    "0",
                    "16"
                ],
                [
                    "0",
                    "18"
                ],
                [
                    "0",
                    "21"
                ],
                [
                    "0",
                    "23"
                ],
                [
                    "0",
                    "25"
                ],
                [
                    "0",
                    "28"
                ],
                [
                    "0",
                    "29"
                ],
                [
                    "1",
                    "2"
                ],
                [
                    "1",
                    "3"
                ],
                [
                    "1",
                    "8"
                ],
                [
                    "1",
                    "7"
                ],
                [
                    "1",
                    "4"
                ],
                [
                    "1",
                    "12"
                ],
                [
                    "2",
                    "13"
                ],
                [
                    "2",
                    "14"
                ],
                [
                    "2",
                    "17"
                ],
                [
                    "2",
                    "20"
                ],
                [
                    "2",
                    "31"
                ],
                [
                    "2",
                    "33"
                ],
                [
                    "2",
                    "34"
                ],
                [
                    "4",
                    "5"
                ],
                [
                    "4",
                    "7"
                ],
                [
                    "5",
                    "7"
                ],
                [
                    "5",
                    "12"
                ],
                [
                    "5",
                    "24"
                ],
                [
                    "5",
                    "26"
                ],
                [
                    "5",
                    "28"
                ],
                [
                    "5",
                    "35"
                ],
                [
                    "8",
                    "12"
                ],
                [
                    "8",
                    "14"
                ],
                [
                    "8",
                    "19"
                ],
                [
                    "9",
                    "27"
                ],
                [
                    "27",
                    "30"
                ],
                [
                    "30",
                    "32"
                ]
            ],
            "positions": {
                "0": [
                    -0.18600383576206533,
                    -0.021213345543855122
                ],
                "1": [
                    -0.06927362336032365,
                    -0.04681557045494816
                ],
                "2": [
                    -0.006701472734059084,
                    0.11801072325962739
                ],
                "3": [
                    -0.2266515895080552,
                    0.09936662668496603
                ],
                "4": [
                    -0.18322546678429188,
                    -0.12997172310151478
                ],
                "5": [
                    -0.005264075902365807,
                    -0.2129359534826339
                ],
                "7": [
                    -0.10192004833104704,
                    -0.19466646026766693
                ],
                "8": [
                    0.037698312760846786,
                    0.024115264126918806
                ],
                "9": [
                    0.6481542666063457,
                    0.274498936127183
                ],
                "11": [
                    -0.383238829566485,
                    -0.33538938055456924
                ],
                "12": [
                    0.05165205052178154,
                    -0.10590388792856327
                ],
                "13": [
                    0.4386527712716972,
                    -0.13777086136602543
                ],
                "14": [
                    0.16230045578008018,
                    0.08063257459405299
                ],
                "16": [
                    -0.4340051150189461,
                    0.08691499759342254
                ],
                "17": [
                    -0.2438470323364909,
                    0.5011948140138319
                ],
                "18": [
                    -0.4559918838181664,
                    0.32724329036428124
                ],
                "19": [
                    -0.11518181724316405,
                    0.37759476356872057
                ],
                "20": [
                    0.40276860287188654,
                    0.10738650348490031
                ],
                "21": [
                    -0.5726575765998787,
                    0.1753162525059082
                ],
                "23": [
                    -0.5606933339790803,
                    -0.22957698920595077
                ],
                "24": [
                    0.05505537405853271,
                    -0.5462584767932959
                ],
                "25": [
                    -0.18962247256894438,
                    -0.4435074089682197
                ],
                "26": [
                    0.3171255211283282,
                    -0.36435597996876457
                ],
                "27": [
                    0.600733664958752,
                    0.4964577388892406
                ],
                "28": [
                    -0.2286516216608736,
                    -0.2388081810237044
                ],
                "29": [
                    -0.6039396158259869,
                    -0.043762041434559695
                ],
                "30": [
                    0.4542211057589451,
                    0.6770586477050295
                ],
                "31": [
                    0.34926328326795064,
                    0.28084812824487987
                ],
                "32": [
                    0.24829782444077886,
                    0.7932762464430829
                ],
                "33": [
                    0.17012870675770037,
                    0.41227338112938816
                ],
                "34": [
                    0.01961053284765936,
                    0.45927764804369575
                ],
                "35": [
                    0.21072633080653955,
                    -0.4740569176524492
                ]
            }
        },
        {
            "nodes": [
                "0",
                "1",
                "2",
                "3",
                "4",
                "5",
                "7",
                "8",
                "9",
                "10",
                "11",
                "12",
                "13",
                "14",
                "16",
                "17",
                "18",
                "19",
                "20",
                "21",
                "22",
                "23",
                "24",
                "25",
                "26",
                "27",
                "28",
                "29",
                "30",
                "31",
                "32",
                "33",
                "34",
                "35"
            ],
            "links": [
                [
                    "0",
                    "1"
                ],
                [
                    "0",
                    "2"
                ],
                [
                    "0",
                    "7"
                ],
                [
                    "0",
                    "3"
                ],
                [
                    "0",
                    "11"
                ],
                [
                    "0",
                    "12"
                ],
                [
                    "0",
                    "16"
                ],
                [
                    "0",
                    "18"
                ],
                [
                    "0",
                    "21"
                ],
                [
                    "0",
                    "23"
                ],
                [
                    "0",
                    "25"
                ],
                [
                    "0",
                    "28"
                ],
                [
                    "0",
                    "29"
                ],
                [
                    "1",
                    "2"
                ],
                [
                    "1",
                    "3"
                ],
                [
                    "1",
                    "7"
                ],
                [
                    "1",
                    "5"
                ],
                [
                    "1",
                    "4"
                ],
                [
                    "1",
                    "12"
                ],
                [
                    "2",
                    "5"
                ],
                [
                    "2",
                    "9"
                ],
                [
                    "2",
                    "13"
                ],
                [
                    "2",
                    "14"
                ],
                [
                    "2",
                    "17"
                ],
                [
                    "2",
                    "20"
                ],
                [
                    "2",
                    "31"
                ],
                [
                    "2",
                    "32"
                ],
                [
                    "2",
                    "33"
                ],
                [
                    "2",
                    "34"
                ],
                [
                    "4",
                    "5"
                ],
                [
                    "4",
                    "7"
                ],
                [
                    "5",
                    "7"
                ],
                [
                    "5",
                    "12"
                ],
                [
                    "5",
                    "22"
                ],
                [
                    "5",
                    "24"
                ],
                [
                    "5",
                    "26"
                ],
                [
                    "5",
                    "28"
                ],
                [
                    "5",
                    "35"
                ],
                [
                    "7",
                    "10"
                ],
                [
                    "8",
                    "12"
                ],
                [
                    "8",
                    "14"
                ],
                [
                    "8",
                    "19"
                ],
                [
                    "9",
                    "27"
                ],
                [
                    "30",
                    "32"
                ]
            ],
            "positions": {
                "0": [
                    -0.09253019084934977,
                    -0.005247498076702467
                ],
                "1": [
                    -0.04244018375694303,
                    -0.010460717186592944
                ],
                "2": [
                    0.009541755143436859,
                    0.058076849054708723
                ],
                "3": [
                    -0.16169517004957054,
                    0.06735372177417996
                ],
                "4": [
                    -0.1179412833259918,
                    -0.07037057292014072
                ],
                "5": [
                    -0.0054963773624715495,
                    -0.062397149432217996
                ],
                "7": [
                    -0.047891359359794994,
                    -0.09587423062801625
                ],
                "8": [
                    -0.016553738485036384,
                    0.17139622421316592
                ],
                "9": [
                    0.37446256528996175,
                    0.1572319151676574
                ],
                "10": [
                    -0.10205810733839654,
                    -0.3954074690817012
                ],
                "11": [
                    -0.3107795001104914,
                    -0.2543223396232706
                ],
                "12": [
                    0.02640952438859956,
                    -0.012247476850535621
                ],
                "13": [
                    0.329147657447924,
                    -0.09594231607064585
                ],
                "14": [
                    0.129019519467939,
                    0.0930616352582682
                ],
                "16": [
                    -0.3763677230198209,
                    0.05239784778460449
                ],
                "17": [
                    -0.17697874856005602,
                    0.3407503344451313
                ],
                "18": [
                    -0.32393582057431963,
                    0.22517838965030318
                ],
                "19": [
                    -0.17004060114289593,
                    0.4748752516473318
                ],
                "20": [
                    0.32699926278140534,
                    0.03529079183700966
                ],
                "21": [
                    -0.39768418729513744,
                    0.13117043624693428
                ],
                "22": [
                    0.18340402278441192,
                    -0.246329217437552
                ],
                "23": [
                    -0.39036874488008777,
                    -0.1615971714347862
                ],
                "24": [
                    0.025743618624052056,
                    -0.3845981762285568
                ],
                "25": [
                    -0.1933341164340363,
                    -0.33051060737306615
                ],
                "26": [
                    0.2558436614800186,
                    -0.250694181965299
                ],
                "27": [
                    0.5645980109977906,
                    0.3814112253977858
                ],
                "28": [
                    -0.12403297276351977,
                    -0.1479982474454471
                ],
                "29": [
                    -0.42076064786596207,
                    -0.046373970895819905
                ],
                "30": [
                    0.350036608879035,
                    0.6080192829911698
                ],
                "31": [
                    0.2641760502506885,
                    0.20963421445772154
                ],
                "32": [
                    0.1294508021884083,
                    0.42014577750329196
                ],
                "33": [
                    0.13728534526634872,
                    0.30979631450567646
                ],
                "34": [
                    -0.02000408984145008,
                    0.35922872280953677
                ],
                "35": [
                    0.1376506792316674,
                    -0.34841396298740057
                ]
            }
        }
    ]
}